README.md
pyproject.toml
setup.py
pyd4/__init__.py
pyd4.egg-info/PKG-INFO
pyd4.egg-info/SOURCES.txt
pyd4.egg-info/dependency_links.txt
pyd4.egg-info/not-zip-safe
pyd4.egg-info/requires.txt
pyd4.egg-info/top_level.txt